sqlite_server/__init__.py
sqlite_server/client.py
sqlite_server/exceptions.py
sqlite_server/server.py
sqlite_server-0.1.2.dist-info/METADATA
sqlite_server-0.1.2.dist-info/WHEEL
sqlite_server-0.1.2.dist-info/top_level.txt
sqlite_server-0.1.2.dist-info/RECORD
