Metadata-Version: 2.1
Name: sqlite-server
Version: 0.1.2
Summary: On request SQLite server
Author: osmocode
License: MIT
Platform: UNKNOWN
Requires-Dist: Pyro5
